{
    "agent": "Conditional3",
    "domain": "highway",
    "fps": 7,
    "frames_dir": "/home/yotama/OneDrive/Local_Git/Agent-Interview/backend/static/run_2022-12-11_15:36:51_uid:123/Highlight_Frames",
    "num_trajectories": 4,
    "output_dir": "/home/yotama/OneDrive/Local_Git/Agent-Interview/backend/static/run_2022-12-11_15:36:51_uid:123",
    "pause": 0,
    "predicates": [
        "behind",
        "infrontof",
        "above",
        "below",
        "lane1",
        "lane2",
        "lane3",
        "lane4",
        "slow",
        "fast",
        "collision"
    ],
    "query_data": {
        "constraint_s_e": "None",
        "constraint_s_e_p1": "None",
        "constraint_s_e_p2": "None",
        "csrf_token": "IjhiODNmNDRmMjJkMWQyMTU5NTY4YjZkYWYxNTA2YjIwMzU4OGFlZTci.Y5Xc4g.roRJTXRHovgp9mOf4aIFvh2YvLE",
        "end_lane": "None",
        "end_pos": "None",
        "end_speed": "None",
        "pre_padding": true,
        "start_lane": "None",
        "start_pos": "None",
        "start_speed": "None",
        "submit": false
    },
    "seq_max_len": null,
    "seq_min_len": 21,
    "trace_constrains": {},
    "user_id": "123",
    "videos_dir": "/home/yotama/OneDrive/Local_Git/Agent-Interview/backend/static/run_2022-12-11_15:36:51_uid:123/Highlight_Videos"
}